{
  "base_price": 1495,
  "beamstation_catalog_url": "https://beamstation.com/datasets",
  "beamstation_origin": "https://beamstation.com",
  "category_group_name": "Restaurants",
  "config_category": "sales",
  "config_description": "--High-Volume, Active targets--\n\nPopular restaurants sitting in the Top 20% of their local market for proven foot traffic and review volume within the last 30 days and a market scope of 10km. \n\nThese are the highest-velocity, actively transacting accounts for payment processing, POS systems, and supply chain sales.\n\nValidated by an \"Active Heartbeat\" signal.",
  "config_name": "Top 20% Active Restaurant Review Whales in Philadelphia-Camden-Wilmington Metro Area, PA-NJ-DE-MD, US",
  "export_job_id": "60cd24ac-2352-496c-84fb-955e874171dc",
  "github_org": "Beamstation-Datasets",
  "id_short": 942005,
  "location_name": "Philadelphia-Camden-Wilmington, PA-NJ-DE-MD",
  "location_type": "metro",
  "repo_name": "top-20-active-restaurant-review-whales-in-philadelphia-camden-wilmington-metro-are-sample-942005",
  "sample_b2_path": "b2-export:BeamStation-ExportFiles/942005/beamstation_942005_restaurants-us-philadelphiacamdenwilmingtonpanjdemd_SAMPLE_DIST.csv",
  "sample_pct": 9.95,
  "sample_records": 151,
  "sample_sha256": "15ffd0744906dd4fba21c27d1afb7cf5c78f5cafdea36cd761b28f1ba22cd063",
  "sample_size_bytes": 569171,
  "total_records": 1518,
  "updated_at": "2026-04-16T22:38:57.032576+00:00"
}